sv_dlp/__init__.py
sv_dlp/__main__.py
sv_dlp/update.py
sv_dlp/version.py
sv_dlp/download/__init__.py
sv_dlp/download/postdownload.py
sv_dlp/download/tiles.py
sv_dlp/services/__init__.py
sv_dlp/services/bing.py
sv_dlp/services/naver.py
sv_dlp/services/yandex.py
sv_dlp/services/apple/__init__.py
sv_dlp/services/apple/auth.py
sv_dlp/services/apple/geo.py
sv_dlp/services/apple/proto/MapTile_pb2.py
sv_dlp/services/apple/proto/__init__.py
sv_dlp/services/baidu/__init__.py
sv_dlp/services/baidu/geo.py
sv_dlp/services/google/__init__.py
sv_dlp/services/google/protobuf.py
sv_dlp/services/google/url_protobuf.py
sv_dlp/services/google/util.py
sv_dlp-2024.1.5.dist-info/LICENSE
sv_dlp-2024.1.5.dist-info/METADATA
sv_dlp-2024.1.5.dist-info/WHEEL
sv_dlp-2024.1.5.dist-info/entry_points.txt
sv_dlp-2024.1.5.dist-info/top_level.txt
sv_dlp-2024.1.5.dist-info/RECORD
