Metadata-Version: 2.1
Name: sv-dlp
Version: 2024.1.5
Summary: Flexible Street View API Wrapper for Python 
Home-page: https://github.com/shmugoh/sv-dlp
Maintainer: shmugo
Maintainer-email: juan@shmugo.co
License: UNKNOWN
Platform: UNKNOWN
Requires-Python: >=3.10
License-File: LICENSE
Requires-Dist: altgraph ==0.17.4
Requires-Dist: certifi ==2023.7.22
Requires-Dist: charset-normalizer ==3.3.2
Requires-Dist: colorama ==0.4.6
Requires-Dist: future ==0.18.3
Requires-Dist: idna ==3.4
Requires-Dist: packaging ==23.2
Requires-Dist: pefile ==2023.2.7
Requires-Dist: piexif ==1.1.3
Requires-Dist: Pillow ==10.1.0
Requires-Dist: pillow-heif ==0.13.1
Requires-Dist: protobuf ==4.25.0
Requires-Dist: pycryptodome ==3.19.1
Requires-Dist: pyinstaller ==6.1.0
Requires-Dist: pyinstaller-hooks-contrib ==2023.10
Requires-Dist: pyproj ==3.6.1
Requires-Dist: pywin32-ctypes ==0.2.2
Requires-Dist: requests ==2.31.0
Requires-Dist: tqdm ==4.66.1
Requires-Dist: urllib3 ==2.0.7
